lormsq/__init__.py
lormsq-0.0.6.dist-info/LICENCE
lormsq-0.0.6.dist-info/METADATA
lormsq-0.0.6.dist-info/WHEEL
lormsq-0.0.6.dist-info/top_level.txt
lormsq-0.0.6.dist-info/RECORD
